bbc_pole-0.1.1.dist-info/licenses/LICENSE
pole/__init__.py
pole/async_utils.py
pole/clipboard.py
pole/config.py
pole/guess.py
pole/text_art.py
pole/vault.py
bbc_pole-0.1.1.dist-info/METADATA
bbc_pole-0.1.1.dist-info/WHEEL
bbc_pole-0.1.1.dist-info/entry_points.txt
bbc_pole-0.1.1.dist-info/top_level.txt
bbc_pole-0.1.1.dist-info/RECORD
