Metadata-Version: 2.4
Name: bbc-pole
Version: 0.1.1
Summary: Pole is a high-level `vault` tool for more conveniently finding and reading secrets.
License-File: LICENSE
Requires-Dist: hvac
Requires-Dist: pyperclip
Requires-Dist: platformdirs
Requires-Dist: notify_py
Requires-Dist: tomli; python_version < "3.11"
Dynamic: license-file
